Workbook

Sheet Dashboard
A1: Date | B1: Starting Cash | C1: Income | D1: Bills | E1: Available After Bills | F1: Credit Card Payment | G1: Ending Cash
A2: 45827 | B2: 3690.67 | C2: =SUMIFS(Income!C:C, Income!A:A, A2) -> 0 | D2: =SUMIFS(Bills!C:C, Bills!A:A, ">" & A2, Bills!A:A, "<=" & A2) -> 0 | E2: =B2+C2-D2 -> 3690.67 | F2: =3002.54 -> 3002.54 | G2: =E2-F2 -> 688.13
A3: 45828 | B3: =G2 -> 688.13 | C3: =SUMIFS(Income!C:C, Income!A:A, A3) -> 4032 | D3: =SUMIFS(Bills!C:C, Bills!A:A, ">" & A2, Bills!A:A, "<=" & A3) -> 572 | E3: =B3+C3-D3 -> 4148.13 | F3: =2600 -> 2600 | G3: =E3-F3 -> 1548.13
A4: 45841 | B4: =G3 -> 1548.13 | C4: =SUMIFS(Income!C:C, Income!A:A, A4) -> 3569 | D4: =SUMIFS(Bills!C:C, Bills!A:A, ">" & A3, Bills!A:A, "<=" & A4) -> 1462.51 | E4: =B4+C4-D4 -> 3654.62 | F4: =ROUND(E4*0.9, 2) -> 3289.16 | G4: =E4-F4+205.15 -> 570.61
A5: 45849 | B5: =G4 -> 570.61 | C5: =SUMIFS(Income!C:C, Income!A:A, A5) -> 2240 | D5: =SUMIFS(Bills!C:C, Bills!A:A, ">" & A4, Bills!A:A, "<=" & A5) -> -1422.97 | E5: =B5+C5-D5 -> 4233.58 | F5: =ROUND(E5*0.9, 2) -> 3810.22 | G5: =E5-F5 -> 423.36
A6: 45856 | B6: =G5 -> 423.36 | C6: =SUMIFS(Income!C:C, Income!A:A, A6) -> 3569 | D6: =SUMIFS(Bills!C:C, Bills!A:A, ">" & A5, Bills!A:A, "<=" & A6) -> 1534.33 | E6: =B6+C6-D6 -> 2458.03 | F6: =829 + 554 -> 1383 | G6: =E6-F6 -> 1075.03
A7: 45870 | B7: =G6 -> 1075.03 | C7: =SUMIFS(Income!C:C, Income!A:A, A7) -> 3569 | D7: =SUMIFS(Bills!C:C, Bills!A:A, ">" & A6, Bills!A:A, "<=" & A7) -> -886.81 | E7: =B7+C7-D7 -> 5530.84 | F7: =ROUND(E7*0.9, 2) -> 4977.76 | G7: =E7-F7 -> 553.08
A8: 45877 | B8: =G7 -> 553.08 | C8: =SUMIFS(Income!C:C, Income!A:A, A8) -> 5400 | D8: =SUMIFS(Bills!C:C, Bills!A:A, ">" & A7, Bills!A:A, "<=" & A8) -> -4170.27 | E8: =B8+C8-D8 -> 10123.35 | F8: 500 | G8: =E8-F8 -> 9623.35
A9: 45884 | B9: =G8 -> 9623.35 | C9: =SUMIFS(Income!C:C, Income!A:A, A9) -> 3569 | D9: =SUMIFS(Bills!C:C, Bills!A:A, ">" & A8, Bills!A:A, "<=" & A9) -> 2035 | E9: =B9+C9-D9 -> 11157.35 | F9: 500 | G9: =E9-F9 -> 10657.35
A10: 45898 | B10: =G9 -> 10657.35 | C10: =SUMIFS(Income!C:C, Income!A:A, A10) -> 3569 | D10: =SUMIFS(Bills!C:C, Bills!A:A, ">" & A9, Bills!A:A, "<=" & A10) -> 1728.71 | E10: =B10+C10-D10 -> 12497.64 | F10: 2500 | G10: =E10-F10 -> 9997.64
A11: 45908 | B11: =G10 -> 9997.64 | C11: =SUMIFS(Income!C:C, Income!A:A, A11) -> 11880 | D11: =SUMIFS(Bills!C:C, Bills!A:A, ">" & A10, Bills!A:A, "<=" & A11) -> -1690.74 | E11: =B11+C11-D11 -> 23568.38 | F11: 1500 | G11: =E11-F11 -> 22068.38
A12: 45912 | B12: =G11 -> 22068.38 | C12: =SUMIFS(Income!C:C, Income!A:A, A12) -> 3569 | D12: =SUMIFS(Bills!C:C, Bills!A:A, ">" & A11, Bills!A:A, "<=" & A12) -> 2628.3 | E12: =B12+C12-D12 -> 23009.08 | F12: 1500 | G12: =E12-F12 -> 21509.08
A13: 45926 | B13: =G12 -> 21509.08 | C13: =SUMIFS(Income!C:C, Income!A:A, A13) -> 3569 | D13: =SUMIFS(Bills!C:C, Bills!A:A, ">" & A12, Bills!A:A, "<=" & A13) -> 12413.49 | E13: =B13+C13-D13 -> 12664.59 | F13: 0 | G13: =E13-F13 -> 12664.59
A14: 45940 | B14: =G13 -> 12664.59 | C14: =SUMIFS(Income!C:C, Income!A:A, A14) -> 12209 | D14: =SUMIFS(Bills!C:C, Bills!A:A, ">" & A13, Bills!A:A, "<=" & A14) -> 13357.99 | E14: =B14+C14-D14 -> 11515.6 | F14: 0 | G14: =E14-F14 -> 11515.6

Sheet Bills
A1: Due Date | B1: Description | C1: Amount | D1: Frequency | E1: Notes
A2: 45827 | B2: Lillys Dance | C2: 50 | D2: One-time
A3: 45828 | B3: Turbo Tax | C3: 322 | D3: One-time | E3: Auto-draft
A4: 45828 | B4: Adderral | C4: 210 | D4: One-time | E4: Auto-Draft
A5: 45828 | B5: Amex | C5: 40 | D5: Monthly
A6: 45829 | B6: Cell Phone | C6: 197.97 | D6: Monthly | E6: Auto-draft
A7: 45838 | B7: Internet | C7: 89.99 | D7: Monthly | E7: Auto-draft
A8: 45838 | B8: HOA Fee | C8: -182.25 | D8: One-time | E8: HOA Past Due Balance
A9: 45838 | B9: Robinhood CC | C9: -500 | D9: One-time | E9: Robinhood Credit Card Payment
A10: 45839 | B10: Mortgage | C10: =SUM(1069.29,1068) -> 2137.29 | D10: Monthly | E10: Auto-draft
A11: 45839 | B11: USC Rec | C11: 52 | D11: Monthly | E11: Posts to Robinhood CC
A12: 45839 | B12: HOA Fees | C12: -170 | D12: Monthly | E12: Auto-draft
A13: 45840 | B13: Sewage | C13: -162.49 | D13: Monthly | E13: Auto-draft
A14: 45842 | B14: BMW Lease | C14: -1072.69 | D14: Monthly | E14: Auto-draft
A15: 45845 | B15: Credit Card Payment | C15: -400 | D15: One-time | E15: Robinhood Credit Card Payment
A16: 45842 | B16: Water | C16: -107.03 | D16: Monthly | E16: Posts to Robinhood CC
A17: 45845 | B17: Electric | C17: -106.39 | D17: Monthly | E17: Auto-draft
A18: 45845 | B18: Peoples Gas | C18: -85.86 | D18: Monthly
A19: 45845 | B19: GLP-1 | C19: 349 | D19: Monthly | E19: Auto-draft
A20: 45852 | B20: BMW Payment | C20: 1534.33 | D20: Monthly | E20: Auto-draft
A21: 45859 | B21: Cell Phone | C21: 197.37 | D21: Monthly | E21: Auto-draft
A22: 45860 | B22: RH Credit Card | C22: -1000 | D22: One-time
A23: 45863 | B23: RH Credit Card | C23: -1000 | D23: One-time
A24: 45863 | B24: Chase Credit Card | C24: -1000 | D24: One-time
A25: 45868 | B25: Big Green Egg | C25: -324.52 | D25: Monthly | E25: Auto-draft
A26: 45868 | B26: Internet | C26: -89.99 | D26: Monthly | E26: Auto-draft, reimbursed by Brittany's work
A27: 45870 | B27: HII Pay | C27: 3569.33 | D27: Bi-Weekly
A28: 45870 | B28: Mortgage | C28: -1069 | D28: Monthly | E28: Auto-draft
A29: 45870 | B29: HOA Fees | C29: -170 | D29: Monthly | E29: Auto-draft
A30: 45873 | B30: BMW Lease | C30: -1072.63 | D30: Monthly | E30: Auto-draft
A31: 45873 | B31: Sewage | C31: -105.58 | D31: Monthly | E31: Auto-draft
A32: 45873 | B32: Water | C32: -107.03 | D32: Monthly | E32: Auto-draft
A33: 45876 | B33: Electric | C33: -203.59 | D33: Monthly | E33: Auto-draft
A34: 45874 | B34: Robinhood CC | C34: -1000 | D34: One-time
A35: 45875 | B35: Peoples Gas | C35: -92.14 | D35: Monthly | E35: Auto-draft
A36: 45877 | B36: Deep Creek Lake | C36: -1589.3 | D36: One-time
A37: 45882 | B37: BMW | C37: -1534.33 | D37: Monthly | E37: Auto-draft
A38: 45884 | B38: HII Pay | C38: 3569.33 | D38: Bi-Weekly
A39: 45887 | B39: Brandon & Lo Room Deposit | C39: -370.13 | D39: One-time
A40: 45887 | B40: Brittany Birthday Gifts | C40: -1118 | D40: One-time
A41: 45890 | B41: Cell Phone | C41: -197.97 | D41: Monthly | E41: Auto-draft
A42: 45899 | B42: Internet | C42: -89.99 | D42: Monthly | E42: Auto-draft, reimbursed by Brittany's work
A43: 45898 | B43: Big Green Egg | C43: -324.52 | D43: Monthly | E43: Auto-draft
A44: 45898 | B44: HII Pay | C44: 3569.33 | D44: Bi-Weekly
A45: 45898 | B45: HOA Fees | C45: 170 | D45: Monthly
A46: 45901 | B46: Mortgage | C46: -1069 | D46: Monthly | E46: Auto-draft
A47: 45904 | B47: Sewage | C47: =-13.69 -> -13.69 | D47: Monthly | E47: Auto-draft
A48: 45904 | B48: Peoples Gas | C48: =-71.76 -> -71.76 | D48: Monthly | E48: Auto-draft
A49: 45904 | B49: Water | C49: =-114.54 -> -114.54 | D49: Monthly | E49: Auto-draft
A50: 45904 | B50: Electric | C50: =-191.18 -> -191.18 | D50: Monthly | E50: Auto-draft
A51: 45908 | B51: GLP-1 | C51: -349 | D51: Monthly | E51: Auto-draft
A52: 45908 | B52: Golf Clubs | C52: 208.42 | D52: Monthly | E52: Auto-draft
A53: 45919 | B53: FERC Pay | C53: 9045 | D53: Bi-Weekly
A54: 45912 | B54: HII Pay | C54: 4162.3 | D54: Bi-Weekly
A55: 45912 | B55: BMW | C55: -1534 | D55: Monthly | E55: Auto-draft
A56: 45922 | B56: Cell Phone | C56: -200.51 | D56: Monthly | E56: Auto-draft
A57: 45926 | B57: HII Pay | C57: 3569 | D57: Bi-Weekly
A58: 45929 | B58: Big Green Egg | C58: -324.52 | D58: Monthly | E58: Auto-draft
A59: 45930 | B59: Internet | C59: -89.99 | D59: Monthly | E59: Auto-draft, reimbursed by Brittany's work
A60: 45931 | B60: HOA Fees | C60: =-170/2 -> -85 | D60: Monthly | E60: Auto-draft
A61: 45931 | B61: Mortgage | C61: -1069 | D61: Monthly | E61: Auto-draft
A62: 45933 | B62: Sewage | C62: -185.73 | D62: Monthly | E62: Auto-draft
A63: 45933 | B63: Water | C63: -88.26 | D63: Monthly | E63: Auto-draft from RH card
A64: 45933 | B64: FERC Pay | C64: 1622.85 | D64: Bi-Weekly
A65: 45937 | B65: GLP-1 | C65: -349 | D65: Monthly | E65: Auto-draft
A66: 45937 | B66: Peoples Gas | C66: -99.8 | D66: Monthly | E66: Auto-draft
A67: 45938 | B67: Golf Clubs | C67: -208.42 | D67: Monthly | E67: Auto-draft
A68: 45938 | B68: Electric | C68: -156.64 | D68: Monthly | E68: Auto-draft
A69: 45936 | B69: FERC Pay | C69: 10822.5 | D69: Monthly
A70: 45938 | B70: HII Pay | C70: 3569 | D70: Bi-Weekly
A71: 45943 | B71: BMW 430i | C71: -411 | D71: Monthly | E71: Auto-draft
A72: 45943 | B72: BMW | C72: -1534 | D72: Monthly | E72: Auto-draft
A73: 45952 | B73: Cell Phone | C73: -200.51 | D73: Monthly | E73: Auto-draft
A74: 45954 | B74: HII Pay | C74: 3569 | D74: Bi-Weekly
A75: 45954 | B75: SoFi Invest | C75: -1000 | D75: Bi-Weekly
A76: 45959 | B76: Big Green Egg | C76: -324.52 | D76: Monthly | E76: Auto-draft
A77: 45960 | B77: Internet | C77: -89.99 | D77: Monthly | E77: Auto-draft, reimbursed by Brittany's work
A78: 45964 | B78: HOA Fees | C78: =-170 -> -170 | D78: Monthly | E78: Auto-draft
A79: 45962 | B79: Mortgage | C79: -1069 | D79: Monthly | E79: Auto-draft
A80: 45964 | B80: Sewage | C80: -103.62 | D80: Monthly | E80: Auto-draft
A81: 45964 | B81: Water | C81: -105.44 | D81: Monthly | E81: Auto-draft from RH card
A82: 45968 | B82: HII Pay | C82: 3569 | D82: Bi-Weekly
A83: 45968 | B83: Peoples Gas | C83: =-133.64 -> -133.64 | D83: Monthly | E83: Auto-draft
A84: 45968 | B84: XGIMI | C84: =-136.36 -> -136.36 | D84: Monthly | E84: Auto-draft
A85: 45968 | B85: Golf Clubs | C85: -208.42 | D85: Monthly | E85: Auto-draft
A86: 45968 | B86: Electric | C86: =SUM(C83:C85) -> -478.42 | D86: Monthly | E86: Auto-draft
A87: 45974 | B87: BMW 430i | C87: -411 | D87: Monthly | E87: Manual payment to Britt
A88: 45974 | B88: BMW | C88: 1895-10-18 | D88: Monthly | E88: Auto-draft
A89: 45982 | B89: HII Pay | C89: 3569 | D89: Bi-Weekly
A90: 45990 | B90: Big Green Egg | C90: -324.52 | D90: Monthly | E90: Auto-draft
A91: 45991 | B91: Internet | C91: -89.99 | D91: Monthly | E91: Auto-draft, reimbursed by Britt's work
A92: 45992 | B92: HOA Fees | C92: =-170 -> -170 | D92: Monthly | E92: Auto-draft
A93: 45992 | B93: Mortgage | C93: -1069 | D93: Monthly | E93: Auto-draft
A94: 45994 | B94: Sewage | C94: -117.31 | D94: Monthly | E94: Auto-draft
A95: 45994 | B95: Water | C95: -118.62 | D95: Monthly | E95: Auto-draft from RH card
A96: 45996 | B96: HII Pay | C96: 3569 | D96: Bi-Weekly
A97: 45998 | B97: Peoples Gas | C97: =-157.08 -> -157.08 | D97: Monthly | E97: Auto-draft
A98: 45998 | B98: XGIMI | C98: =-136.36 -> -136.36 | D98: Monthly | E98: Auto-draft
A99: 45968 | B99: Electric | C99: =-125.47 -> -125.47 | D99: Monthly | E99: Auto-draft
A100: 46004 | B100: BMW 430i | C100: -411 | D100: Monthly | E100: Auto-draft
...

Sheet Income
A1: Date | B1: Source | C1: Amount
A2: 45828 | B2: Paycheck | C2: 4032
A3: 45841 | B3: Paycheck | C3: 3569
A4: 45849 | B4: Paycheck | C4: 2240
A5: 45856 | B5: Paycheck | C5: 3569
A6: 45870 | B6: Paycheck | C6: 3569
A7: 45877 | B7: Paycheck | C7: 5400
A8: 45884 | B8: Paycheck | C8: 3569
A9: 45898 | B9: Paycheck | C9: 3569
A10: 45908 | B10: Paycheck | C10: 11880
A11: 45912 | B11: Paycheck | C11: 3569
A12: 45926 | B12: Paycheck | C12: 3569
A13: 45940 | B13: Paycheck | C13: 3569
A14: 45940 | B14: Paycheck | C14: 8640

Sheet Debt Tracker
A1: Card Name | B1: Balance | C1: Interest Rate | D1: Min Payment | E1: Target Payment
A2: Chase Saffire Reserve | B2: =9602.54 - 3002.54 -> 6600 | C2: 24% | D2: 210 | E2: 4000
A3: Capital One | B3: 935 | C3: 22% | D3: 180 | E3: 200
A4: Robinhood | B4: 8494.43 | C4: 22% | D4: 100 | E4: 1000
A11: =SUM(-922.06,Bills!C70:C73,12339,-3000) -> 9840.43
